{
	"pages": [
		{
			"path": "pages/index/index",
			"style": {
				"navigationBarTitleText": "首页"
			}
		},
		{
			"path": "pages/category/index",
			"style": {
				"navigationBarTitleText": "商品分类"
			}
		},
		{
			"path": "pages/cart/index",
			"style": {
				"navigationBarTitleText": "购物车"
			}
		},
		{
			"path": "pages/user/index",
			"style": {
				"navigationBarTitleText": "我的"
			}
		},
		{
			"path": "pages/search/index",
			"style": {
				"navigationBarTitleText": "搜索"
			}
		},
		{
			"path": "pages/goods_list/index",
			"style": {
				"navigationBarTitleText": "商品列表"
			}
		}
	],
	"globalStyle": {
		"navigationBarTextStyle": "white",
		"navigationBarTitleText": "黑马优购",
		"navigationBarBackgroundColor": "#EA4350",
		"backgroundColor": "#F8F8F8"
	},
	"tabBar": {
		"color": "#000",
		"selectedColor": "#E03440",
		"list": [
		  {
			"pagePath": "pages/index/index",
			"text": "首页",
			"iconPath": "/static/index.png",
			"selectedIconPath": "/static/index_selected.png"
		  },
		  {
			"pagePath": "pages/category/index",
			"text": "分类",
			"iconPath": "/static/category.png",
			"selectedIconPath": "/static/category_selected.png"
		  },
		  {
			"pagePath": "pages/cart/index",
			"text": "购物车",
			"iconPath": "/static/cart.png",
			"selectedIconPath": "/static/cart_selected.png"
		  },
		  {
			"pagePath": "pages/user/index",
			"text": "我的",
			"iconPath": "/static/cart.png",
			"selectedIconPath": "/static/cart_selected.png"
		  }
		]
	  },
	"condition" : { //模式配置，仅开发期间生效
		"current": 0, //当前激活的模式(list 的索引项)
		"list": [
			{
				"name": "", //模式名称
				"path": "", //启动页面，必选
				"query": "" //启动参数，在页面的onLoad函数里面得到
			}
		]
	}
}
